[
  {
    "rank": "3598",
    "name": "Crimecash CGOLD",
    "price": "$1,016.30",
    "change": "99.86%",
    "volume": "$391,587"
  },
  {
    "rank": "3584",
    "name": "DOFI",
    "price": "$0.000298",
    "change": "97.15%",
    "volume": "$410,961"
  },
  {
    "rank": "3547",
    "name": "Anti-Lockdown",
    "price": "$0.000617",
    "change": "91.06%",
    "volume": "$430,092"
  },
  {
    "rank": "2163",
    "name": "Ducato Protocol Token",
    "price": "$0.2975",
    "change": "85.53%",
    "volume": "$399,667"
  },
  {
    "rank": "3557",
    "name": "Shira inu",
    "price": "$0.0...01618",
    "change": "80.40%",
    "volume": "$434,529"
  },
  {
    "rank": "4510",
    "name": "La Casa De Papel",
    "price": "$0.00002313",
    "change": "77.49%",
    "volume": "$76,089"
  },
  {
    "rank": "3856",
    "name": "Escape from the Matrix",
    "price": "$0.00000002746",
    "change": "72.68%",
    "volume": "$236,148"
  },
  {
    "rank": "2964",
    "name": "Truth Technology",
    "price": "$0.0511",
    "change": "72.21%",
    "volume": "$3,759,192"
  },
  {
    "rank": "4800",
    "name": "BitGoo",
    "price": "$0.0000003922",
    "change": "63.78%",
    "volume": "$53,404"
  },
  {
    "rank": "3615",
    "name": "Kuber Finance",
    "price": "$0.003148",
    "change": "61.93%",
    "volume": "$373,283"
  },
  {
    "rank": "4228",
    "name": "SherlockDoge",
    "price": "$0.0...06611",
    "change": "61.57%",
    "volume": "$121,612"
  },
  {
    "rank": "3881",
    "name": "HarmonyPad",
    "price": "$0.00997",
    "change": "60.45%",
    "volume": "$205,431"
  },
  {
    "rank": "4156",
    "name": "SnowFloki",
    "price": "$0.0000002903",
    "change": "59.06%",
    "volume": "$139,309"
  },
  {
    "rank": "4408",
    "name": "ZinaX Token",
    "price": "$0.3308",
    "change": "54.31%",
    "volume": "$93,102"
  },
  {
    "rank": "2359",
    "name": "DINGO TOKEN",
    "price": "$0.0...08883",
    "change": "51.06%",
    "volume": "$63,172"
  },
  {
    "rank": "2004",
    "name": "ALL BEST ICO",
    "price": "$0.0009091",
    "change": "49.45%",
    "volume": "$394,972"
  },
  {
    "rank": "4572",
    "name": "Demeter",
    "price": "$0.01003",
    "change": "47.56%",
    "volume": "$72,589"
  },
  {
    "rank": "4662",
    "name": "MetaSafeMoon",
    "price": "$0.0...04752",
    "change": "47.46%",
    "volume": "$64,898"
  },
  {
    "rank": "3683",
    "name": "IDEAS",
    "price": "$0.001071",
    "change": "47.13%",
    "volume": "$324,217"
  },
  {
    "rank": "4513",
    "name": "BakerGuild",
    "price": "$0.06474",
    "change": "44.02%",
    "volume": "$78,909"
  },
  {
    "rank": "2998",
    "name": "CryptoDiceHero",
    "price": "$0.1775",
    "change": "39.85%",
    "volume": "$3,133,066"
  },
  {
    "rank": "4490",
    "name": "RoboShib",
    "price": "$0.0000007692",
    "change": "39.65%",
    "volume": "$81,832"
  },
  {
    "rank": "4041",
    "name": "Catena X",
    "price": "$0.02672",
    "change": "38.43%",
    "volume": "$166,202"
  },
  {
    "rank": "2860",
    "name": "Gold Nugget",
    "price": "$104.87",
    "change": "37.63%",
    "volume": "$9,228,798"
  },
  {
    "rank": "1238",
    "name": "PLATINCOIN",
    "price": "$1.22",
    "change": "35.12%",
    "volume": "$79,665"
  },
  {
    "rank": "3953",
    "name": "HbarPad",
    "price": "$0.006694",
    "change": "35.04%",
    "volume": "$193,721"
  },
  {
    "rank": "4120",
    "name": "EternalFlow",
    "price": "$0.000000002627",
    "change": "34.87%",
    "volume": "$145,659"
  },
  {
    "rank": "3565",
    "name": "H-Space Metaverse",
    "price": "$0.00004137",
    "change": "34.36%",
    "volume": "$410,952"
  },
  {
    "rank": "4637",
    "name": "SafeDogecoin",
    "price": "$0.006064",
    "change": "34.03%",
    "volume": "$66,245"
  },
  {
    "rank": "3727",
    "name": "Talkado",
    "price": "$0.0...03245",
    "change": "33.95%",
    "volume": "$299,029"
  }
]